plamo_translate/__init__.py
plamo_translate/main.py
plamo_translate/assets/chat_template.jinja2
plamo_translate/clients/__init__.py
plamo_translate/clients/translate.py
plamo_translate/servers/__init__.py
plamo_translate/servers/utils.py
plamo_translate/servers/llamacpp/__init__.py
plamo_translate/servers/llamacpp/server.py
plamo_translate/servers/mlx/__init__.py
plamo_translate/servers/mlx/server.py
plamo_translate-1.0.5.dist-info/METADATA
plamo_translate-1.0.5.dist-info/WHEEL
plamo_translate-1.0.5.dist-info/entry_points.txt
plamo_translate-1.0.5.dist-info/licenses/LICENSE
plamo_translate-1.0.5.dist-info/RECORD
