Metadata-Version: 2.4
Name: plamo-translate
Version: 1.0.5
Summary: A command-line interface for translation using the plamo-2-translate model with local execution.
Author-email: Shunta Saito <shunta@preferred.jp>
License-Expression: Apache-2.0
License-File: LICENSE
Keywords: deep learning,machine translation,mlx,mlx-lm,natural language processing,nlp,plamo,plamo-translate,plamo-translate-cli,sentencepiece,transformer
Classifier: Development Status :: 5 - Production/Stable
Classifier: Environment :: Console
Classifier: Environment :: MacOS X
Classifier: Intended Audience :: Developers
Classifier: License :: OSI Approved :: Apache Software License
Classifier: Operating System :: MacOS
Classifier: Programming Language :: Python :: 3
Classifier: Programming Language :: Python :: 3.10
Classifier: Programming Language :: Python :: 3.11
Classifier: Programming Language :: Python :: 3.12
Classifier: Programming Language :: Python :: 3.13
Classifier: Topic :: Utilities
Requires-Python: >=3.10
Requires-Dist: mcp[cli]>=1.9.2
Requires-Dist: mlx-lm>=0.26.3; sys_platform == 'darwin'
Requires-Dist: numba>=0.60.0
